pycarde/__init__.py
pycarde/card.py
pycarde/constants.py
pycarde/image.py
pycarde/macro.py
pycarde/raw.py
pycarde/save.py
pycarde/serializer.py
pycarde/util.py
pycarde/compression/__init__.py
pycarde/compression/pkviewer.py
pycarde/compression/util.py
pycarde/compression/vpk.py
pycarde/compression/data/__init__.py
pycarde/compression/data/textbuffer_jp.dat
pycarde/compression/data/textbuffer_us.dat
pycarde/data/__init__.py
pycarde/data/dcguide.png
pycarde/data/save.dat
pycarde/data/short_jp.dat
pycarde/misc/__init__.py
pycarde/misc/_save.py
pycarde/misc/_util.py
pycarde-0.8.7.dist-info/LICENSE
pycarde-0.8.7.dist-info/METADATA
pycarde-0.8.7.dist-info/WHEEL
pycarde-0.8.7.dist-info/top_level.txt
pycarde-0.8.7.dist-info/RECORD
